ablang2/__init__.py
ablang2/load_model.py
ablang2/pretrained.py
ablang2/models/__init__.py
ablang2/models/ablang1/__init__.py
ablang2/models/ablang1/embedding.py
ablang2/models/ablang1/encoderblocks.py
ablang2/models/ablang1/extra_fns.py
ablang2/models/ablang1/fairseq_mha.py
ablang2/models/ablang1/model.py
ablang2/models/ablang1/pretrained.py
ablang2/models/ablang1/tokenizers.py
ablang2/models/ablang2/__init__.py
ablang2/models/ablang2/ablang.py
ablang2/models/ablang2/encoderblock.py
ablang2/models/ablang2/tokenizers.py
ablang2/models/ablang2/vocab.py
ablang2/pretrained_utils/__init__.py
ablang2/pretrained_utils/alignment.py
ablang2/pretrained_utils/encodings.py
ablang2/pretrained_utils/extra_utils.py
ablang2/pretrained_utils/restoration.py
ablang2/pretrained_utils/scores.py
ablang2-0.2.1.dist-info/LICENSE
ablang2-0.2.1.dist-info/METADATA
ablang2-0.2.1.dist-info/WHEEL
ablang2-0.2.1.dist-info/top_level.txt
ablang2-0.2.1.dist-info/RECORD
