Metadata-Version: 2.1
Name: ablang2
Version: 0.2.1
Summary: AbLang2: An antibody-specific language model focusing on NGL prediction.
Home-page: 
Author: Tobias Hegelund Olsen
Maintainer: Tobias Hegelund Olsen
Maintainer-email: tobiasheol@gmail.com
License: BSD 3-clause license
License-File: LICENSE
Requires-Dist: torch >1.9
Requires-Dist: requests
Requires-Dist: einops
Requires-Dist: rotary-embedding-torch
Requires-Dist: numpy
